hump/__init__.py
hump/exceptions.py
hump/models.py
hump/server.py
hump/statuses.py
hump-1.1.0.dist-info/licenses/LICENSE
hump-1.1.0.dist-info/METADATA
hump-1.1.0.dist-info/WHEEL
hump-1.1.0.dist-info/top_level.txt
hump-1.1.0.dist-info/RECORD
