Metadata-Version: 2.4
Name: hump
Version: 1.1.0
Summary: Hump (a defining part of grizzly's neck) is a zero-dependency simple async web server framework for registering request handlers
Author-email: Nikita Belomestnykh <medbeebs@gmail.com>
License-Expression: MIT
Project-URL: Homepage, https://github.com/medbeebs/hump
Project-URL: Repository, https://github.com/medbeebs/hump
Project-URL: Issues, https://github.com/medbeebs/hump/issues
Classifier: Intended Audience :: Information Technology
Classifier: Intended Audience :: System Administrators
Classifier: Operating System :: OS Independent
Classifier: Programming Language :: Python :: 3
Classifier: Programming Language :: Python
Classifier: Topic :: Internet
Classifier: Topic :: Software Development :: Libraries :: Application Frameworks
Classifier: Topic :: Software Development :: Libraries :: Python Modules
Classifier: Topic :: Software Development :: Libraries
Classifier: Topic :: Software Development
Classifier: Typing :: Typed
Classifier: Development Status :: 4 - Beta
Classifier: Environment :: Web Environment
Classifier: Framework :: AsyncIO
Classifier: Intended Audience :: Developers
Classifier: Programming Language :: Python :: 3 :: Only
Classifier: Programming Language :: Python :: 3.13
Classifier: Programming Language :: Python :: 3.14
Classifier: Topic :: Internet :: WWW/HTTP :: HTTP Servers
Classifier: Topic :: Internet :: WWW/HTTP
Requires-Python: >=3.13
License-File: LICENSE
Requires-Dist: orjson>=3.11.4
Dynamic: license-file
